bcloud_core/RequestCookie.py
bcloud_core/__init__.py
bcloud_core/auth.py
bcloud_core/const.py
bcloud_core/decoder.py
bcloud_core/encoder.py
bcloud_core/hasher.py
bcloud_core/log.py
bcloud_core/net.py
bcloud_core/pcs.py
bcloud_core/util.py
bcloud_core-3.8.2.dev1.dist-info/DESCRIPTION.rst
bcloud_core-3.8.2.dev1.dist-info/METADATA
bcloud_core-3.8.2.dev1.dist-info/RECORD
bcloud_core-3.8.2.dev1.dist-info/WHEEL
bcloud_core-3.8.2.dev1.dist-info/metadata.json
bcloud_core-3.8.2.dev1.dist-info/top_level.txt
